matsubplots/__init__.py
matsubplots/matsubplots.py
matsubplots/version.py
matsubplots/viewers.py
matsubplots-1.4.0.dist-info/licenses/LICENSE.md
matsubplots-1.4.0.dist-info/METADATA
matsubplots-1.4.0.dist-info/WHEEL
matsubplots-1.4.0.dist-info/top_level.txt
matsubplots-1.4.0.dist-info/RECORD
