Metadata-Version: 2.4
Name: matsubplots
Version: 1.4.0
Summary: Better subplots for matplotlib.
Author: Ali Uneri
Project-URL: Homepage, https://auneri.github.io/matsubplots
Project-URL: Repository, https://github.com/auneri/matsubplots
Classifier: Framework :: Matplotlib
Classifier: License :: OSI Approved :: MIT License
Classifier: Operating System :: OS Independent
Classifier: Programming Language :: Python :: 3
Requires-Python: >=3.8
License-File: LICENSE.md
Requires-Dist: matplotlib
Requires-Dist: numpy
Provides-Extra: flake8
Requires-Dist: flake8; extra == "flake8"
Requires-Dist: flake8-bugbear; extra == "flake8"
Requires-Dist: flake8-builtins; extra == "flake8"
Requires-Dist: flake8-comprehensions; extra == "flake8"
Requires-Dist: flake8-docstrings; extra == "flake8"
Requires-Dist: flake8-import-order; extra == "flake8"
Requires-Dist: flake8-mutable; extra == "flake8"
Requires-Dist: flake8-pyproject; extra == "flake8"
Requires-Dist: flake8-quotes; extra == "flake8"
Requires-Dist: flake8-use-fstring; extra == "flake8"
Requires-Dist: flake8-use-pathlib; extra == "flake8"
Requires-Dist: pep8-naming; extra == "flake8"
Dynamic: license-file
